LICENSE.md
README.md
pyproject.toml
setup.cfg
setup.py
adminlte3/__init__.py
adminlte3/apps.py
adminlte3/apps.pyi
adminlte3/context_processors.py
adminlte3/context_processors.pyi
adminlte3/menus.py
adminlte3/renderers.py
adminlte3/renderers.pyi
adminlte3/admin/__init__.py
adminlte3/admin/admin.py
adminlte3/admin/admin.pyi
adminlte3/admin/apps.py
adminlte3/admin/apps.pyi
adminlte3/admin/context_processors.py
adminlte3/admin/context_processors.pyi
adminlte3/admin/widgets.py
adminlte3/admin/widgets.pyi
adminlte3/admin/templates/admin/actions.html
adminlte3/admin/templates/admin/app_index.html
adminlte3/admin/templates/admin/app_list.html
adminlte3/admin/templates/admin/base.html
adminlte3/admin/templates/admin/base_site.html
adminlte3/admin/templates/admin/change_form.html
adminlte3/admin/templates/admin/change_form_object_tools.html
adminlte3/admin/templates/admin/change_list.html
adminlte3/admin/templates/admin/change_list_results.html
adminlte3/admin/templates/admin/filter.html
adminlte3/admin/templates/admin/filters.html
adminlte3/admin/templates/admin/index.html
adminlte3/admin/templates/admin/login.html
adminlte3/admin/templates/admin/object_history.html
adminlte3/admin/templates/admin/pagination.html
adminlte3/admin/templates/admin/search_form.html
adminlte3/admin/templates/admin/submit_line.html
adminlte3/admin/templates/admin/includes/fieldset.html
adminlte3/admin/templates/admin/widgets/clearable_file_input.html
adminlte3/admin/templates/admin/widgets/foreign_key_raw_id.html
adminlte3/admin/templates/admin/widgets/many_to_many_raw_id.html
adminlte3/admin/templates/admin/widgets/radio.html
adminlte3/admin/templates/admin/widgets/related_widget_wrapper.html
adminlte3/admin/templates/admin/widgets/split_datetime.html
adminlte3/admin/templates/admin/widgets/url.html
adminlte3/admin/templates/admin_ref/404.html
adminlte3/admin/templates/admin_ref/500.html
adminlte3/admin/templates/admin_ref/actions.html
adminlte3/admin/templates/admin_ref/app_index.html
django_theme_adminlte3.egg-info/PKG-INFO
django_theme_adminlte3.egg-info/SOURCES.txt
django_theme_adminlte3.egg-info/dependency_links.txt
django_theme_adminlte3.egg-info/requires.txt
django_theme_adminlte3.egg-info/top_level.txt