Metadata-Version: 2.1
Name: django-theme-adminlte3
Version: 3.2.0.12
Summary: Django Admin LTE v3 Theme
Home-page: https://github.com/kelsoncm/django-theme-adminlte3
Download-URL: https://github.com/kelsoncm/django-theme-adminlte3/releases
Author: Kelson da Costa Medeiros
Author-email: kelsoncm@gmail.com
License: MIT license
Keywords: django,admin lte,theme
Classifier: Development Status :: 4 - Beta
Classifier: Intended Audience :: Developers
Classifier: License :: OSI Approved :: MIT License
Classifier: Operating System :: OS Independent
Classifier: Programming Language :: JavaScript
Classifier: Programming Language :: Python :: 3.9
Classifier: Programming Language :: Python :: 3.10
Classifier: Programming Language :: Python :: 3.11
Classifier: Framework :: Django :: 4.0
Classifier: Framework :: Pytest
Classifier: Topic :: Internet :: WWW/HTTP
Classifier: Topic :: Software Development :: Libraries :: Python Modules
Classifier: Natural Language :: English
Classifier: Natural Language :: Portuguese (Brazilian)
Requires-Python: >=3.10
License-File: LICENSE.md
Requires-Dist: Django>=5.0
Requires-Dist: pillow>=10.3.0
